zimfarm/__init__.py
zimfarm/client.py
zimfarm/utils.py
zimfarm/commands/__init__.py
zimfarm/commands/login.py
zimfarm/commands/logout.py
zimfarm/commands/zimfarm.py
zimfarm/errors/__init__.py
zimfarm/errors/oauth2.py
zimfarm/models/__init__.py
zimfarm/models/base.py
zimfarm/models/worker.py
zimfarm-0.0.10.dist-info/LICENSE
zimfarm-0.0.10.dist-info/METADATA
zimfarm-0.0.10.dist-info/WHEEL
zimfarm-0.0.10.dist-info/entry_points.txt
zimfarm-0.0.10.dist-info/top_level.txt
zimfarm-0.0.10.dist-info/RECORD
