Metadata-Version: 2.1
Name: zimfarm
Version: 0.0.10
Summary: Zimfarm Client
Home-page: https://github.com/openzim/zimfarm-client
Author: Chris Li
Author-email: chris@kiwix.com
License: UNKNOWN
Platform: UNKNOWN
Classifier: Development Status :: 1 - Planning
Classifier: Intended Audience :: Developers
Classifier: License :: OSI Approved :: GNU Lesser General Public License v3 (LGPLv3)
Classifier: Natural Language :: English
Classifier: Programming Language :: Python :: 3.7
Requires-Dist: requests (>=2.21.0)
